{"language":"polish","itemid":"398676","app[content][legal]":"","app[content][earlyaccess_description]":"","app[content][about]":"[h2][b]O ścieżce dźwiękowej[/b][/h2]\r\n\r\nTa ścieżka dźwiękowa została stworzona dla gry The Colorful Creature. Na częściowo popularne życzenie gracze chcieli oficjalnej ścieżki dźwiękowej do gry i jesteśmy tutaj, aby ją dostarczyć. Ciesz się ponad 40 utworami zawartymi w tej playliście!\r\n\r\nTa oficjalna ścieżka dźwiękowa zawiera playlistę z większością utworów w nieskompresowanym formacie .wav. Ta playlista będzie aktualizowana, gdy gra podstawowa również otrzyma zupełnie nowe utwory!\r\n\r\n[b]WAŻNE: [/b] Jeśli Steam się zawiesza podczas odtwarzania utworów, to z powodu odtwarzacza muzyki Steam. Po prostu znajdź utwory tam, gdzie je pobrałeś i słuchaj ich stamtąd.","app[content][short_description]":"Ta ścieżka dźwiękowa została stworzona dla gry The Colorful Creature. Na częściowo popularne życzenie gracze chcieli oficjalnej ścieżki dźwiękowej do gry i jesteśmy tutaj, aby ją dostarczyć. Ciesz się ponad 40 utworami zawartymi w tej playliście!","app[content][sysreqs][mac][min][osversion]":"","app[content][sysreqs][mac][min][processor]":"","app[content][sysreqs][mac][min][graphics]":"","app[content][sysreqs][mac][min][soundcard]":"","app[content][sysreqs][mac][min][vrsupport]":"","app[content][sysreqs][mac][min][notes]":"","app[content][sysreqs][mac][req][osversion]":"","app[content][sysreqs][mac][req][processor]":"","app[content][sysreqs][mac][req][graphics]":"","app[content][sysreqs][mac][req][soundcard]":"","app[content][sysreqs][mac][req][vrsupport]":"","app[content][sysreqs][mac][req][notes]":"","app[content][sysreqs][windows][min][osversion]":"","app[content][sysreqs][windows][min][processor]":"","app[content][sysreqs][windows][min][graphics]":"","app[content][sysreqs][windows][min][soundcard]":"","app[content][sysreqs][windows][min][vrsupport]":"","app[content][sysreqs][windows][min][notes]":"","app[content][sysreqs][windows][req][osversion]":"","app[content][sysreqs][windows][req][processor]":"","app[content][sysreqs][windows][req][graphics]":"","app[content][sysreqs][windows][req][soundcard]":"","app[content][sysreqs][windows][req][vrsupport]":"","app[content][sysreqs][windows][req][notes]":"","app[content][sysreqs][linux][min][osversion]":"","app[content][sysreqs][linux][min][processor]":"","app[content][sysreqs][linux][min][graphics]":"","app[content][sysreqs][linux][min][soundcard]":"","app[content][sysreqs][linux][min][vrsupport]":"","app[content][sysreqs][linux][min][notes]":"","app[content][sysreqs][linux][req][osversion]":"","app[content][sysreqs][linux][req][processor]":"","app[content][sysreqs][linux][req][graphics]":"","app[content][sysreqs][linux][req][soundcard]":"","app[content][sysreqs][linux][req][vrsupport]":"","app[content][sysreqs][linux][req][notes]":""}